flaggit
