Metadata-Version: 1.0
Name: django-flaggit
Version: 0.0.2
Summary: Generic content flagging for Django
Home-page: https://github.com/caffeinehit/django-flaggit
Author: Alen Mujezinovic
Author-email: alen@caffeinehit.com
License: UNKNOWN
Platform: UNKNOWN
